dialga_api/__init__.py
dialga_api/scheduler_pb2.py
dialga_api/scheduler_pb2.pyi
dialga_api/scheduler_pb2_grpc.py
dialga_api-1.5.0.dist-info/METADATA
dialga_api-1.5.0.dist-info/WHEEL
dialga_api-1.5.0.dist-info/top_level.txt
dialga_api-1.5.0.dist-info/RECORD
