Metadata-Version: 2.4
Name: dialga-api
Version: 1.5.0
Classifier: Development Status :: 3 - Alpha
Classifier: Intended Audience :: Developers
Classifier: License :: OSI Approved :: MIT License
Classifier: Programming Language :: Python :: 3
Classifier: Programming Language :: Python :: 3.12
Requires-Dist: grpcio
Requires-Dist: protobuf>=3.19.0
Dynamic: classifier
Dynamic: requires-dist
